statsy/Constants.py
statsy/Conversion.py
statsy/Logarithms.py
statsy/Methods.py
statsy/Probability.py
statsy/__init__.py
statsy/main.py
statsy-0.3.0.dist-info/METADATA
statsy-0.3.0.dist-info/WHEEL
statsy-0.3.0.dist-info/top_level.txt
statsy-0.3.0.dist-info/RECORD
