Metadata-Version: 2.1
Name: statsy
Version: 0.3.0
Summary: A package of statistical functions and operations.
License: Apache License 2.0
Requires-Python: >=3.6
Requires-Dist: numpy>=1.25.0
